MANIFEST.in
README.md
setup.cfg
setup.py
ensemblizer/__init__.py
ensemblizer/ensemblizer.py
ensemblizer.egg-info/PKG-INFO
ensemblizer.egg-info/SOURCES.txt
ensemblizer.egg-info/dependency_links.txt
ensemblizer.egg-info/requires.txt
ensemblizer.egg-info/top_level.txt