Metadata-Version: 2.1
Name: ensemblizer
Version: 0.5
Summary: Package for ensembling models together
Home-page: https://github.com/metriczulu/ensemblizer
Author: Shane Stephenson / metriczulu
Author-email: stephenson.shane.a@gmail.com
License: None
Download-URL: https://github.com/metriczulu/ensemblizer/archive/v0.05.tar.gz
Platform: UNKNOWN
